quclo/__init__.py
quclo/backend.py
quclo/circuit.py
quclo/config.py
quclo/execution.py
quclo/main.py
quclo/models.py
quclo/proxy.py
quclo/user.py
quclo/utils.py
quclo-0.0.5.dist-info/METADATA
quclo-0.0.5.dist-info/WHEEL
quclo-0.0.5.dist-info/entry_points.txt
quclo-0.0.5.dist-info/RECORD
