Metadata-Version: 2.1
Name: quclo
Version: 0.0.5
Summary: A CLI tool designed to simplify the execution and management of quantum circuits across multiple backend providers.
Author: QuClo
Author-email: info@quclo.com
Requires-Python: >=3.12,<4.0
Classifier: Programming Language :: Python :: 3
Classifier: Programming Language :: Python :: 3.12
Requires-Dist: click (>=8.1.7,<9.0.0)
Requires-Dist: openqasm3[all] (>=1.0.0,<2.0.0)
Requires-Dist: pydantic[email] (>=2.8.2,<3.0.0)
Requires-Dist: pyqir (>=0.10.3,<0.11.0)
Requires-Dist: requests (>=2.32.3,<3.0.0)
